babulus/__init__.py
babulus/__main__.py
babulus/audio_dsl.py
babulus/cache_resolver.py
babulus/cli.py
babulus/compiler.py
babulus/config.py
babulus/elevenlabs_pronunciation.py
babulus/errors.py
babulus/media.py
babulus/models.py
babulus/parser.py
babulus/sfx_workflow.py
babulus/static_assets.py
babulus/transcript.py
babulus/util.py
babulus/voiceover_dsl.py
babulus/voiceover_generate.py
babulus/yaml_parser.py
babulus/music/__init__.py
babulus/music/dry_run.py
babulus/music/elevenlabs_music.py
babulus/music/providers.py
babulus/music/registry.py
babulus/sfx/__init__.py
babulus/sfx/dry_run.py
babulus/sfx/elevenlabs_sfx.py
babulus/sfx/providers.py
babulus/sfx/registry.py
babulus/tts/__init__.py
babulus/tts/azure_tts.py
babulus/tts/dry_run.py
babulus/tts/elevenlabs_tts.py
babulus/tts/openai_tts.py
babulus/tts/polly_tts.py
babulus/tts/providers.py
babulus/tts/registry.py
babulus-0.3.0.dist-info/licenses/LICENSE
babulus-0.3.0.dist-info/METADATA
babulus-0.3.0.dist-info/WHEEL
babulus-0.3.0.dist-info/entry_points.txt
babulus-0.3.0.dist-info/top_level.txt
babulus-0.3.0.dist-info/RECORD
