Metadata-Version: 2.4
Name: babulus
Version: 0.3.0
Summary: Narration-first DSL + audio pipeline for Remotion videos
Author-email: Ryan Porter <ryan.porter@anthus.ai>
License: MIT
Project-URL: Homepage, https://github.com/AnthusAI/Babulus
Project-URL: Documentation, https://github.com/AnthusAI/Babulus/tree/main/docs
Project-URL: Repository, https://github.com/AnthusAI/Babulus
Project-URL: Issues, https://github.com/AnthusAI/Babulus/issues
Keywords: video,remotion,dsl,tts,narration,audio,elevenlabs,yaml
Classifier: Development Status :: 3 - Alpha
Classifier: Intended Audience :: Developers
Classifier: License :: OSI Approved :: MIT License
Classifier: Programming Language :: Python :: 3
Classifier: Programming Language :: Python :: 3.11
Classifier: Programming Language :: Python :: 3.12
Classifier: Topic :: Multimedia :: Sound/Audio :: Speech
Classifier: Topic :: Multimedia :: Video
Classifier: Topic :: Software Development :: Code Generators
Requires-Python: >=3.11
License-File: LICENSE
Requires-Dist: PyYAML>=6.0.1
Requires-Dist: requests>=2.31.0
Requires-Dist: chardet>=5.2.0
Requires-Dist: dotyaml>=0.1.3
Requires-Dist: boto3>=1.34.0
Provides-Extra: dev
Requires-Dist: pytest>=8.0; extra == "dev"
Requires-Dist: pytest-asyncio>=0.23; extra == "dev"
Requires-Dist: black; extra == "dev"
Requires-Dist: ruff; extra == "dev"
Requires-Dist: python-semantic-release>=9.0.0; extra == "dev"
Dynamic: license-file
